snpio/__init__.py
snpio/benchmark_json.py
snpio/run_snpio.py
snpio/analysis/__init__.py
snpio/analysis/allele_summary_stats.py
snpio/analysis/genotype_encoder.py
snpio/analysis/tree_parser.py
snpio/docs/HEADER.yaml
snpio/docs/Makefile
snpio/docs/admonitions-filter.lua
snpio/docs/admonitions.tex
snpio/docs/listings-setup.tex
snpio/docs/make.bat
snpio/docs/metadata.yaml
snpio/docs/requirements.txt
snpio/docs/template.tex
snpio/docs/dev/versioning.md
snpio/docs/source/changelog.md
snpio/docs/source/changelog.rst
snpio/docs/source/conf.py
snpio/docs/source/example_script.rst
snpio/docs/source/getting_started.rst
snpio/docs/source/index.rst
snpio/docs/source/refs.bib
snpio/docs/source/snpio.analysis.rst
snpio/docs/source/snpio.filtering.rst
snpio/docs/source/snpio.io.rst
snpio/docs/source/snpio.plotting.rst
snpio/docs/source/snpio.popgenstats.rst
snpio/docs/source/snpio.rst
snpio/docs/source/_static/custom.css
snpio/docs/source/generated/snpio.GenePopReader.rst
snpio/docs/source/generated/snpio.GenotypeEncoder.rst
snpio/docs/source/generated/snpio.NRemover2.rst
snpio/docs/source/generated/snpio.PhylipReader.rst
snpio/docs/source/generated/snpio.Plotting.rst
snpio/docs/source/generated/snpio.PopGenStatistics.rst
snpio/docs/source/generated/snpio.SNPioMultiQC.rst
snpio/docs/source/generated/snpio.StructureReader.rst
snpio/docs/source/generated/snpio.TreeParser.rst
snpio/docs/source/generated/snpio.VCFReader.rst
snpio/docs/source/generated/snpio.analysis.genotype_encoder.GenotypeEncoder.rst
snpio/docs/source/generated/snpio.analysis.tree_parser.TreeParser.rst
snpio/docs/source/generated/snpio.filtering.nremover2.NRemover2.rst
snpio/docs/source/generated/snpio.io.genepop_reader.GenePopReader.rst
snpio/docs/source/generated/snpio.io.phylip_reader.PhylipReader.rst
snpio/docs/source/generated/snpio.io.structure_reader.StructureReader.rst
snpio/docs/source/generated/snpio.io.vcf_reader.VCFReader.rst
snpio/docs/source/generated/snpio.plotting.plotting.Plotting.rst
snpio-1.6.8.dist-info/licenses/LICENSE
snpio-1.6.8.dist-info/METADATA
snpio-1.6.8.dist-info/WHEEL
snpio-1.6.8.dist-info/entry_points.txt
snpio-1.6.8.dist-info/top_level.txt
snpio-1.6.8.dist-info/RECORD
