Metadata-Version: 2.4
Name: snpio
Version: 1.6.8
Summary: SNPio is a Python API for population genetic file processing, filtering, and analysis. It is designed to be a user-friendly tool for the manipulation of population genetic data in a variety of formats. SNPio can be used to filter data based on missingness, MAF and MAC, singletons, biallelic, and monomorphic sites. It can also generate summary statistics for population genetic analyses.
Author-email: "Drs. Bradley T. Martin and Tyler K. Chafin" <evobio721@gmail.com>
License: GPL-3.0-or-later
Project-URL: Source Code, https://github.com/btmartin721/SNPio
Project-URL: Bug Tracker, https://github.com/btmartin721/SNPio/issues
Project-URL: Documentation, https://snpio.readthedocs.io/en/latest/
Project-URL: Changelog, https://snpio.readthedocs.io/en/latest/changelog.html
Keywords: genomics,bioinformatics,population genetics,SNP,VCF,PHYLIP,STRUCTURE,missing data,filtering,filter,MAF,minor allele frequency,MAC,minor allele count,biallelic,monomorphic,singleton,population structure,d-statistics,Fst,multiqc,encoding
Classifier: Development Status :: 5 - Production/Stable
Classifier: Intended Audience :: Science/Research
Classifier: Topic :: Scientific/Engineering :: Bio-Informatics
Classifier: License :: OSI Approved :: GNU General Public License v3 (GPLv3)
Classifier: Programming Language :: Python :: 3
Classifier: Programming Language :: Python :: 3.11
Classifier: Programming Language :: Python :: 3.12
Classifier: Natural Language :: English
Classifier: Operating System :: Unix
Classifier: Operating System :: POSIX
Classifier: Operating System :: MacOS
Requires-Python: <3.13,>=3.11
License-File: LICENSE
Requires-Dist: bokeh
Requires-Dist: h5py
Requires-Dist: holoviews
Requires-Dist: kaleido
Requires-Dist: kneed
Requires-Dist: matplotlib
Requires-Dist: multiqc>=1.29
Requires-Dist: numba
Requires-Dist: numpy
Requires-Dist: pandas
Requires-Dist: panel
Requires-Dist: plotly
Requires-Dist: pysam
Requires-Dist: requests
Requires-Dist: scikit-learn
Requires-Dist: scipy
Requires-Dist: statsmodels
Requires-Dist: seaborn
Requires-Dist: toytree
Requires-Dist: tqdm
Provides-Extra: docs
Requires-Dist: sphinx; extra == "docs"
Requires-Dist: sphinx-rtd-theme; extra == "docs"
Requires-Dist: sphinx-autodoc-typehints; extra == "docs"
Requires-Dist: sphinxcontrib-bibtex; extra == "docs"
Provides-Extra: dev
Requires-Dist: memory-profiler; extra == "dev"
Requires-Dist: psutil; extra == "dev"
Requires-Dist: sphinx; extra == "dev"
Requires-Dist: sphinx-rtd-theme; extra == "dev"
Requires-Dist: sphinx-autodoc-typehints; extra == "dev"
Requires-Dist: sphinxcontrib-bibtex; extra == "dev"
Requires-Dist: pytest; extra == "dev"
Requires-Dist: pre-commit; extra == "dev"
Requires-Dist: pyyaml; extra == "dev"
Dynamic: license-file
